mcp_server_chatgpt/__init__.py
mcp_server_chatgpt/server.py
mcp_server_chatgpt_app-0.1.5.dist-info/METADATA
mcp_server_chatgpt_app-0.1.5.dist-info/WHEEL
mcp_server_chatgpt_app-0.1.5.dist-info/entry_points.txt
mcp_server_chatgpt_app-0.1.5.dist-info/licenses/LICENSE
mcp_server_chatgpt_app-0.1.5.dist-info/RECORD
