Metadata-Version: 2.4
Name: mcp-server-chatgpt-app
Version: 0.1.5
Summary: MCP Server for ChatGPT via AppleScript
Project-URL: Homepage, https://github.com/cdpath/mcp-server-chatgpt-app
Project-URL: Repository, https://github.com/cdpath/mcp-server-chatgpt-app.git
Project-URL: Issues, https://github.com/cdpath/mcp-server-chatgpt-app/issues
Author-email: cdpath <cdpath@outlook.com>
License-Expression: MIT
License-File: LICENSE
Keywords: AppleScript,ChatGPT,mcp
Classifier: Development Status :: 3 - Alpha
Classifier: Intended Audience :: Developers
Classifier: License :: OSI Approved :: MIT License
Classifier: Programming Language :: Python :: 3
Classifier: Programming Language :: Python :: 3.10
Requires-Python: >=3.10
Requires-Dist: mcp>=1.6.0
